pynhd/__init__.py
pynhd/core.py
pynhd/exceptions.py
pynhd/network_tools.py
pynhd/nhdplus_derived.py
pynhd/nldi.py
pynhd/print_versions.py
pynhd/py.typed
pynhd/pygeoapi.py
pynhd/pynhd.py
pynhd-0.19.4.dist-info/METADATA
pynhd-0.19.4.dist-info/WHEEL
pynhd-0.19.4.dist-info/licenses/AUTHORS.rst
pynhd-0.19.4.dist-info/licenses/LICENSE
pynhd-0.19.4.dist-info/RECORD
