Metadata-Version: 2.4
Name: pynhd
Version: 0.19.4
Summary: Access and navigate NHDPlus V2 via various web services, e.g., NLDI and WaterData.
Project-URL: Changelog, https://docs.hyriver.io/changelogs/pynhd.html
Project-URL: CI, https://github.com/hyriver/pynhd/actions
Project-URL: Homepage, https://docs.hyriver.io/readme/pynhd.html
Project-URL: Issues, https://github.com/hyriver/pynhd/issues
Author-email: Taher Chegini <cheginit@gmail.com>
License: MIT
License-File: AUTHORS.rst
License-File: LICENSE
Classifier: Development Status :: 4 - Beta
Classifier: Intended Audience :: Science/Research
Classifier: License :: OSI Approved :: MIT License
Classifier: Operating System :: OS Independent
Classifier: Programming Language :: Python
Classifier: Programming Language :: Python :: 3 :: Only
Classifier: Programming Language :: Python :: 3.9
Classifier: Programming Language :: Python :: 3.10
Classifier: Programming Language :: Python :: 3.11
Classifier: Programming Language :: Python :: 3.12
Classifier: Programming Language :: Python :: 3.13
Classifier: Topic :: Scientific/Engineering
Classifier: Topic :: Scientific/Engineering :: GIS
Classifier: Topic :: Scientific/Engineering :: Hydrology
Classifier: Typing :: Typed
Requires-Python: >=3.9
Requires-Dist: async-retriever<0.20,>=0.19.3
Requires-Dist: cytoolz
Requires-Dist: geopandas>=1
Requires-Dist: networkx
Requires-Dist: numpy>=2
Requires-Dist: pandas>=1
Requires-Dist: pyarrow>=1.0.1
Requires-Dist: pygeoogc<0.20,>=0.19.3
Requires-Dist: pygeoutils<0.20,>=0.19.5
Requires-Dist: shapely>=2
Provides-Extra: nhdplus
Requires-Dist: py7zr; extra == 'nhdplus'
Provides-Extra: test
Requires-Dist: coverage[toml]; extra == 'test'
Requires-Dist: pytest-cov; extra == 'test'
Requires-Dist: pytest-sugar; extra == 'test'
